{
  "articles": [
    {
      "id": "how-to-learn-kanji",
      "slug": "kanji-seekhne-ke-5-tareeqe",
      "title": "کانجی سیکھنے کے 5 مؤثر طریقے",
      "meta_description": "radicals، SRS، mnemonics، context اور writing practice کے ساتھ واضح منصوبہ۔",
      "keywords": "kanji, JLPT, japanese, Kanjidon, kanji seekhne ke 5 tareeqe",
      "read_time": "6 min",
      "faq": [
        {
          "question": "کانجی سیکھنے کے 5 مؤثر طریقے",
          "answer": "radicals، SRS، mnemonics، context اور writing practice کے ساتھ واضح منصوبہ۔"
        },
        {
          "question": "کیا میں Kanjidon کے ساتھ پڑھ سکتا ہوں؟",
          "answer": "جی ہاں۔ Kanjidon کارڈز، مختصر quiz اور spaced repetition کو ملاتا ہے، اس لیے ہر review کا مقصد واضح ہوتا ہے۔"
        }
      ],
      "sections": [
        {
          "type": "intro",
          "content": "چھوٹے قدم سے شروع کریں مگر باقاعدگی سے دہرائیں۔ کانجی کے حصوں کو دیکھیں اور انہیں اصل مثالوں سے جوڑیں۔"
        },
        {
          "type": "heading",
          "level": 2,
          "content": "طریقہ کیوں اہم ہے"
        },
        {
          "type": "text",
          "content": "اچھا منصوبہ recognition، meaning اور وقت پر review کو ملاتا ہے۔ بہت زیادہ نئے characters ایک ساتھ یادداشت کو تھکا دیتے ہیں۔"
        },
        {
          "type": "heading",
          "level": 2,
          "content": "5 عملی قدم"
        },
        {
          "type": "list",
          "items": [
            "مشکل kanji سے پہلے radicals سیکھیں",
            "ہر روز SRS استعمال کریں",
            "ایک بصری کہانی بنائیں",
            "kanji کو context میں پڑھیں",
            "صرف تب لکھیں جب یہ یادداشت میں مدد دے"
          ]
        },
        {
          "type": "heading",
          "level": 2,
          "content": "Kanjidon کیسے مدد کرتا ہے"
        },
        {
          "type": "text",
          "content": "Kanjidon اس routine کو cards، short quiz اور واضح progress میں بدل دیتا ہے۔"
        },
        {
          "type": "heading",
          "level": 2,
          "content": "اگلا قدم"
        },
        {
          "type": "text",
          "content": "آج کے لیے ایک چھوٹا ہدف منتخب کریں، اسے مکمل کریں، اور کل واپس آئیں۔ جب عادت دہرانے میں آسان ہو تو جاپانی بھی آسان ہونے لگتی ہے۔"
        }
      ]
    },
    {
      "id": "how-many-kanji-jlpt",
      "slug": "jlpt-ke-liye-kitne-kanji",
      "title": "JLPT کے لیے کتنے کانجی چاہیے؟",
      "meta_description": "N5 سے N1 تک کانجی کی تعداد اور عملی study plan۔",
      "keywords": "kanji, JLPT, japanese, Kanjidon, jlpt ke liye kitne kanji",
      "read_time": "6 min",
      "faq": [
        {
          "question": "JLPT کے لیے کتنے کانجی چاہیے؟",
          "answer": "N5 سے N1 تک کانجی کی تعداد اور عملی study plan۔"
        },
        {
          "question": "کیا میں Kanjidon کے ساتھ پڑھ سکتا ہوں؟",
          "answer": "جی ہاں۔ Kanjidon کارڈز، مختصر quiz اور spaced repetition کو ملاتا ہے، اس لیے ہر review کا مقصد واضح ہوتا ہے۔"
        }
      ],
      "sections": [
        {
          "type": "intro",
          "content": "چھوٹے قدم سے شروع کریں مگر باقاعدگی سے دہرائیں۔ کانجی کے حصوں کو دیکھیں اور انہیں اصل مثالوں سے جوڑیں۔"
        },
        {
          "type": "heading",
          "level": 2,
          "content": "JLPT سطحیں راستے کے نشان ہیں"
        },
        {
          "type": "text",
          "content": "اچھا منصوبہ recognition، meaning اور وقت پر review کو ملاتا ہے۔ بہت زیادہ نئے characters ایک ساتھ یادداشت کو تھکا دیتے ہیں۔"
        },
        {
          "type": "heading",
          "level": 2,
          "content": "منصوبہ کیسے بنائیں"
        },
        {
          "type": "list",
          "items": [
            "N5: تقریباً 80 kanji",
            "N4: کل تقریباً 240",
            "N3: کل تقریباً 620",
            "N2: کل تقریباً 1,000",
            "N1: تقریباً 2,136 عام kanji"
          ]
        },
        {
          "type": "heading",
          "level": 2,
          "content": "Kanjidon کیسے مدد کرتا ہے"
        },
        {
          "type": "text",
          "content": "Kanjidon اس routine کو cards، short quiz اور واضح progress میں بدل دیتا ہے۔"
        },
        {
          "type": "heading",
          "level": 2,
          "content": "اگلا قدم"
        },
        {
          "type": "text",
          "content": "آج کے لیے ایک چھوٹا ہدف منتخب کریں، اسے مکمل کریں، اور کل واپس آئیں۔ جب عادت دہرانے میں آسان ہو تو جاپانی بھی آسان ہونے لگتی ہے۔"
        }
      ]
    },
    {
      "id": "hiragana-katakana-kanji-differences",
      "slug": "hiragana-katakana-kanji-farq",
      "title": "Hiragana، Katakana اور Kanji: فرق کیا ہے؟",
      "meta_description": "جاپانی writing systems کی ترتیب اور آغاز کا بہترین طریقہ۔",
      "keywords": "kanji, JLPT, japanese, Kanjidon, hiragana katakana kanji farq",
      "read_time": "6 min",
      "faq": [
        {
          "question": "Hiragana، Katakana اور Kanji: فرق کیا ہے؟",
          "answer": "جاپانی writing systems کی ترتیب اور آغاز کا بہترین طریقہ۔"
        },
        {
          "question": "کیا میں Kanjidon کے ساتھ پڑھ سکتا ہوں؟",
          "answer": "جی ہاں۔ Kanjidon کارڈز، مختصر quiz اور spaced repetition کو ملاتا ہے، اس لیے ہر review کا مقصد واضح ہوتا ہے۔"
        }
      ],
      "sections": [
        {
          "type": "intro",
          "content": "چھوٹے قدم سے شروع کریں مگر باقاعدگی سے دہرائیں۔ کانجی کے حصوں کو دیکھیں اور انہیں اصل مثالوں سے جوڑیں۔"
        },
        {
          "type": "heading",
          "level": 2,
          "content": "تین رسم الخط، ایک زبان"
        },
        {
          "type": "text",
          "content": "اچھا منصوبہ recognition، meaning اور وقت پر review کو ملاتا ہے۔ بہت زیادہ نئے characters ایک ساتھ یادداشت کو تھکا دیتے ہیں۔"
        },
        {
          "type": "heading",
          "level": 2,
          "content": "سیکھنے کی ترتیب"
        },
        {
          "type": "list",
          "items": [
            "پہلے hiragana سے شروع کریں",
            "loanwords کے لیے katakana شامل کریں",
            "kanji کو vocabulary کے ساتھ سیکھیں",
            "kanji کو الگ تصویروں کی طرح یاد نہ کریں",
            "شروع ہی میں چھوٹے جملے پڑھیں"
          ]
        },
        {
          "type": "heading",
          "level": 2,
          "content": "Kanjidon کیسے مدد کرتا ہے"
        },
        {
          "type": "text",
          "content": "Kanjidon اس routine کو cards، short quiz اور واضح progress میں بدل دیتا ہے۔"
        },
        {
          "type": "heading",
          "level": 2,
          "content": "اگلا قدم"
        },
        {
          "type": "text",
          "content": "آج کے لیے ایک چھوٹا ہدف منتخب کریں، اسے مکمل کریں، اور کل واپس آئیں۔ جب عادت دہرانے میں آسان ہو تو جاپانی بھی آسان ہونے لگتی ہے۔"
        }
      ]
    },
    {
      "id": "spaced-repetition-kanji",
      "slug": "srs-kanji-kaise-kaam-karta",
      "title": "SRS کانجی کے لیے کیسے کام کرتا ہے؟",
      "meta_description": "spaced repetition یادداشت کو مضبوط کیوں بناتا ہے۔",
      "keywords": "kanji, JLPT, japanese, Kanjidon, srs kanji kaise kaam karta",
      "read_time": "6 min",
      "faq": [
        {
          "question": "SRS کانجی کے لیے کیسے کام کرتا ہے؟",
          "answer": "spaced repetition یادداشت کو مضبوط کیوں بناتا ہے۔"
        },
        {
          "question": "کیا میں Kanjidon کے ساتھ پڑھ سکتا ہوں؟",
          "answer": "جی ہاں۔ Kanjidon کارڈز، مختصر quiz اور spaced repetition کو ملاتا ہے، اس لیے ہر review کا مقصد واضح ہوتا ہے۔"
        }
      ],
      "sections": [
        {
          "type": "intro",
          "content": "چھوٹے قدم سے شروع کریں مگر باقاعدگی سے دہرائیں۔ کانجی کے حصوں کو دیکھیں اور انہیں اصل مثالوں سے جوڑیں۔"
        },
        {
          "type": "heading",
          "level": 2,
          "content": "یادداشت کو صحیح وقت چاہیے"
        },
        {
          "type": "text",
          "content": "اچھا منصوبہ recognition، meaning اور وقت پر review کو ملاتا ہے۔ بہت زیادہ نئے characters ایک ساتھ یادداشت کو تھکا دیتے ہیں۔"
        },
        {
          "type": "heading",
          "level": 2,
          "content": "سادہ SRS routine"
        },
        {
          "type": "list",
          "items": [
            "بھولنے سے پہلے review کریں",
            "sessions مختصر رکھیں",
            "کمزور cards کو ایمانداری سے نشان زد کریں",
            "معنی اور readings کو ملا کر دہرائیں",
            "cramming کے بجائے consistency پر بھروسہ کریں"
          ]
        },
        {
          "type": "heading",
          "level": 2,
          "content": "Kanjidon کیسے مدد کرتا ہے"
        },
        {
          "type": "text",
          "content": "Kanjidon اس routine کو cards، short quiz اور واضح progress میں بدل دیتا ہے۔"
        },
        {
          "type": "heading",
          "level": 2,
          "content": "اگلا قدم"
        },
        {
          "type": "text",
          "content": "آج کے لیے ایک چھوٹا ہدف منتخب کریں، اسے مکمل کریں، اور کل واپس آئیں۔ جب عادت دہرانے میں آسان ہو تو جاپانی بھی آسان ہونے لگتی ہے۔"
        }
      ]
    },
    {
      "id": "100-most-used-kanji",
      "slug": "sab-se-zyada-istemal-100-kanji",
      "title": "سب سے زیادہ استعمال ہونے والے 100 کانجی",
      "meta_description": "سب سے عام 100 کانجی پہلے سیکھنے سے پڑھائی اور JLPT کی بنیاد تیزی سے بنتی ہے۔",
      "keywords": "100 kanji, common kanji, JLPT, Kanjidon, sab se zyada istemal 100 kanji",
      "read_time": "6 min",
      "faq": [
        {
          "question": "سب سے زیادہ استعمال ہونے والے 100 کانجی",
          "answer": "سب سے عام 100 کانجی پہلے سیکھنے سے پڑھائی اور JLPT کی بنیاد تیزی سے بنتی ہے۔"
        },
        {
          "question": "کیا عام kanji پہلے سیکھنے چاہئیں؟",
          "answer": "جی ہاں۔ frequency آپ کو reading میں جلد کامیابی دیتی ہے اور اگلے kanji کو جوڑنا آسان بناتی ہے۔"
        }
      ],
      "sections": [
        {
          "type": "intro",
          "content": "سب سے عام 100 کانجی پہلے سیکھنے سے پڑھائی اور JLPT کی بنیاد تیزی سے بنتی ہے۔"
        },
        {
          "type": "heading",
          "level": 2,
          "content": "سب سے زیادہ استعمال ہونے والے 100 کانجی"
        },
        {
          "type": "text",
          "content": "Frequency is a practical filter: the characters you see every day are the ones that give the fastest return. Learn them with words and short sentences, not as isolated drawings."
        },
        {
          "type": "heading",
          "level": 2,
          "content": "شروع میں نوٹ کرنے والی مثالیں"
        },
        {
          "type": "list",
          "items": [
            "日 (day, sun)",
            "人 (person)",
            "年 (year)",
            "大 (big)",
            "小 (small)",
            "中 (inside, middle)",
            "本 (book, origin)",
            "学 (study)"
          ]
        },
        {
          "type": "heading",
          "level": 2,
          "content": "Kanjidon کیسے مدد کرتا ہے"
        },
        {
          "type": "text",
          "content": "Kanjidon عام kanji کو cards میں بدلتا ہے اور SRS سے دہراتا ہے، اس لیے پہلے سیکھے گئے نشان دوبارہ آتے رہتے ہیں جب تک وہ فطری محسوس نہ ہوں۔"
        }
      ]
    }
  ]
}
